{
    "version": "cep",
    "book_name": "Nahum",
    "book_nr": "34",
    "book": {
        "1": {
            "chapter_nr": 1,
            "chapter": {
                "1": {
                    "verse_nr": 1,
                    "verse": "V\u00fdnos o Ninive. Kniha vid\u011bn\u00ed Nahuma Elk\u00f3\u0161sk\u00e9ho.\n"
                },
                "2": {
                    "verse_nr": 2,
                    "verse": "Hospodin je B\u016fh \u017e\u00e1rliv\u00fd a mstitel. Mstitel je Hospodin, vl\u00e1dce rozho\u0159\u010den\u00fd. Pomstou st\u00edh\u00e1 Hospodin sv\u00e9 protivn\u00edky, hn\u011bvem pron\u00e1sleduje nep\u0159\u00e1tele.\n"
                },
                "3": {
                    "verse_nr": 3,
                    "verse": "Hospodin je shov\u00edvav\u00fd a velkorys\u00fd, ale vin\u00edka bez trestu neponech\u00e1. Jeho cesta vede vich\u0159ic\u00ed a bou\u0159\u00ed, mra\u010dna jsou prach zv\u00ed\u0159en\u00fd jeho nohama.\n"
                },
                "4": {
                    "verse_nr": 4,
                    "verse": "Obo\u0159\u00ed se na mo\u0159e a vysu\u0161\u00ed je, v\u0161echny \u0159eky nech\u00e1 vyschnout. Uvad\u00e1 B\u00e1\u0161an a Karmel, vadne i v\u00fdhonek Liban\u00f3nu.\n"
                },
                "5": {
                    "verse_nr": 5,
                    "verse": "Hory se p\u0159ed n\u00edm t\u0159esou, pahorky se zm\u00edtaj\u00ed, zem\u011b p\u0159ed jeho tv\u00e1\u0159\u00ed se vzdouv\u00e1, sv\u011bt a v\u0161ichni, kte\u0159\u00ed na n\u011bm bydl\u00ed.\n"
                },
                "6": {
                    "verse_nr": 6,
                    "verse": "Kdo odol\u00e1 jeho hrozn\u00e9mu hn\u011bvu? Kdo obstoj\u00ed p\u0159ed jeho planouc\u00edm hn\u011bvem? Jeho rozho\u0159\u010den\u00ed s\u00e1l\u00e1 jak ohe\u0148, sk\u00e1ly se p\u0159ed n\u00edm drol\u00ed.\n"
                },
                "7": {
                    "verse_nr": 7,
                    "verse": "Hospodin je dobr\u00fd, je z\u00e1\u0161titou v den sou\u017een\u00ed, zn\u00e1 se k t\u011bm, kte\u0159\u00ed se k n\u011bmu ut\u00edkaj\u00ed.\n"
                },
                "8": {
                    "verse_nr": 8,
                    "verse": "Val\u00edc\u00ed se povodn\u00ed u\u010din\u00ed konec tomuto m\u00edstu, tma bude pron\u00e1sledovat jeho nep\u0159\u00e1tele.\n"
                },
                "9": {
                    "verse_nr": 9,
                    "verse": "Co zam\u00fd\u0161l\u00edte proti Hospodinu? On u\u010din\u00ed konec. Sou\u017een\u00ed u\u017e podruh\u00e9 nenastane.\n"
                },
                "10": {
                    "verse_nr": 10,
                    "verse": "Zapletou se v hlo\u017e\u00ed sv\u00fdmi pitkami zpiti. Jako such\u00e9 strni\u0161t\u011b budou zcela poz\u0159eni ohn\u011bm.\n"
                },
                "11": {
                    "verse_nr": 11,
                    "verse": "Z tebe vy\u0161el ten, kter\u00fd zam\u00fd\u0161l\u00ed proti Hospodinu zl\u00e9 v\u011bci, ni\u010demn\u00fd r\u00e1dce.\n"
                },
                "12": {
                    "verse_nr": 12,
                    "verse": "Toto prav\u00ed Hospodin: A\u0165 si \u017eij\u00ed sebepokojn\u011bji, a\u0165 je jich sebev\u00edc, budou skoseni; ni\u010demn\u00edk zajde. Poko\u0159oval jsem t\u011b, Sij\u00f3ne, u\u017e t\u011b nebudu poko\u0159ovat.\n"
                },
                "13": {
                    "verse_nr": 13,
                    "verse": "Jeho ja\u0159mo nyn\u00ed p\u0159eraz\u00edm a spadne z tebe, zp\u0159etrh\u00e1m tv\u00e1 pouta.\n"
                },
                "14": {
                    "verse_nr": 14,
                    "verse": "A proti tob\u011b, A\u0161\u00fare, vyd\u00e1v\u00e1 Hospodin p\u0159\u00edkaz: Nebude ji\u017e nikoho, kdo by d\u00e1le rozs\u00e9val tv\u00e9 jm\u00e9no. Z domu tv\u00fdch boh\u016f vyhlad\u00edm modly tesan\u00e9 i lit\u00e9. P\u0159ipravil jsem ti hrob. Jsi zlo\u0159e\u010den\u00fd.\n"
                },
                "15": {
                    "verse_nr": 15,
                    "verse": " \n"
                }
            }
        },
        "2": {
            "chapter_nr": 2,
            "chapter": {
                "1": {
                    "verse_nr": 1,
                    "verse": "Hle, po hor\u00e1ch p\u0159ich\u00e1z\u00ed zv\u011bstovatel radosti, jen\u017e ohla\u0161uje pokoj. Slav, Judo, sv\u00e9 slavnosti, pl\u0148 sv\u00e9 sliby. U\u017e nikdy na tebe nep\u0159it\u00e1hne ni\u010demn\u00edk, je zcela zahlazen.\n"
                },
                "2": {
                    "verse_nr": 2,
                    "verse": "Ninive, u\u017e na tebe t\u00e1hne ten, jen\u017e t\u011b rozmet\u00e1. Jen si hl\u00eddej pevnost. \u010c\u00edhej u cesty. Posilni sv\u00e1 bedra. Seber ve\u0161kerou svou s\u00edlu.\n"
                },
                "3": {
                    "verse_nr": 3,
                    "verse": "Hospodin vr\u00e1t\u00ed J\u00e1kobovi d\u016fstojnost, d\u016fstojnost, jak\u00e1 pat\u0159\u00ed Izraeli. Pot\u0159eli jej vet\u0159elci, zni\u010dili jeho odno\u017ee.\n"
                },
                "4": {
                    "verse_nr": 4,
                    "verse": "Rud\u00fd je \u0161t\u00edt bohat\u00fdr\u016f, v \u0161arlat od\u011bni jsou v\u00e1le\u010dn\u00edci. Jisk\u0159\u00ed jako ohe\u0148 ocel voz\u016f, kdy\u017e se p\u0159ipravuj\u00ed k bitv\u011b. Cyp\u0159i\u0161ov\u00e1 rati\u0161t\u011b se kym\u00e1cej\u00ed.\n"
                },
                "5": {
                    "verse_nr": 5,
                    "verse": "Vozy se \u0161\u00edlen\u011b \u0159\u00edt\u00ed ulicemi, \u017eenou se p\u0159es prostranstv\u00ed podobny pochodn\u00edm, m\u00edhaj\u00ed se jako blesky.\n"
                },
                "6": {
                    "verse_nr": 6,
                    "verse": "S p\u0159ipom\u00ednkou sv\u00fdch vzne\u0161en\u00fdch bo\u017estev klop\u00fdtav\u00fdm b\u011bhem \u017eenou se k ninivsk\u00fdm hradb\u00e1m. Je z\u0159\u00edzen ochrann\u00fd kryt.\n"
                },
                "7": {
                    "verse_nr": 7,
                    "verse": "Br\u00e1ny p\u0159i \u0159ece jsou otev\u0159eny; chr\u00e1m se hrout\u00ed.\n"
                },
                "8": {
                    "verse_nr": 8,
                    "verse": "Je rozhodnuto. Obna\u017eena a odvl\u00e9k\u00e1na je I\u0161tar, jej\u00ed d\u011bvy kv\u00edl\u00ed jako holubice a bij\u00ed se v prsa.\n"
                },
                "9": {
                    "verse_nr": 9,
                    "verse": "Ninive b\u00fdvalo oded\u00e1vna jako rybn\u00edk pln\u00fd vod. A nyn\u00ed ut\u00edkaj\u00ed. Zastavte se, st\u016fjte! Nikdo se v\u0161ak ani neohl\u00e9dne.\n"
                },
                "10": {
                    "verse_nr": 10,
                    "verse": "Rabujte st\u0159\u00edbro, rabujte zlato! Jak\u00e9 nekone\u010dn\u00e9 mno\u017estv\u00ed z\u00e1sob! Jak oslniv\u00fd lesk v\u0161emo\u017en\u00fdch vz\u00e1cnost\u00ed!\n"
                },
                "11": {
                    "verse_nr": 11,
                    "verse": "V\u0161e pust\u00e9! Zpustl\u00e9! Zpusto\u0161en\u00e9! Ztratili odvahu, kolena se t\u0159esou. Smrteln\u00e1 \u00fazkost zachv\u00e1tila ve\u0161ker\u00e1 bedra, tv\u00e1\u0159e v\u0161ech zbledly.\n"
                },
                "12": {
                    "verse_nr": 12,
                    "verse": "Kam se pod\u011blo to doup\u011b lv\u016f, m\u00edsto, kde lv\u00ed\u010data krm\u00edvali? Kdy\u017e lev vych\u00e1zel za ko\u0159ist\u00ed, lv\u00ed\u010de tam z\u016fst\u00e1valo a nikdo je nevypla\u0161il.\n"
                },
                "13": {
                    "verse_nr": 13,
                    "verse": "Lev p\u0159in\u00e1\u0161el hojnost \u00falovku ml\u00e1\u010fat\u016fm, lvic\u00edm to, co zad\u00e1vil, brlohy si napl\u0148oval ko\u0159ist\u00ed, sv\u00e1 doupata t\u00edm, co ulovil. [ (Nahum 2:14) Chyst\u00e1m se v\u0161ak na tebe, je v\u00fdrok Hospodina z\u00e1stup\u016f. Ninivskou vozbu sp\u00e1l\u00edm na prach, tv\u00e1 lv\u00ed\u010data poz\u0159e me\u010d. Vym\u00fdt\u00edm ze zem\u011b tvoje ko\u0159istnictv\u00ed, nebude u\u017e sly\u0161et hlas tv\u00fdch posl\u016f! ]\n"
                }
            }
        },
        "3": {
            "chapter_nr": 3,
            "chapter": {
                "1": {
                    "verse_nr": 1,
                    "verse": "B\u011bda m\u011bstu, je\u017e se brod\u00ed v krvi! Je sam\u00e1 p\u0159etv\u00e1\u0159ka, je pln\u00e9 loupe\u017e\u00ed, ko\u0159ist\u011bn\u00ed nebere konce.\n"
                },
                "2": {
                    "verse_nr": 2,
                    "verse": "Sly\u0161! Bi\u010d\u016f svist, dun\u011bn\u00ed kol! Dusot kon\u00ed, h\u0159mot vozby!\n"
                },
                "3": {
                    "verse_nr": 3,
                    "verse": "\u00datok jezdc\u016f, z\u00e1\u0161lehy me\u010d\u016f, bl\u00fdsk\u00e1n\u00ed kop\u00ed! P\u0159emnoho skolen\u00fdch, hromady mrtv\u00fdch t\u011bl, bezpo\u010det mrtvol, a\u017e p\u0159es n\u011b klop\u00fdtaj\u00ed!\n"
                },
                "4": {
                    "verse_nr": 4,
                    "verse": "To v\u0161echno pro mnoh\u00e1 smilstva Nev\u011bstky, p\u0159esv\u016fdn\u00e9 mistryn\u011b kouzel. Sv\u00fdm smilstvem kup\u010d\u00ed s pron\u00e1rody, sv\u00fdmi kouzly kup\u010d\u00ed s \u010deled\u011bmi.\n"
                },
                "5": {
                    "verse_nr": 5,
                    "verse": "Chyst\u00e1m se v\u0161ak na tebe, je v\u00fdrok Hospodina z\u00e1stup\u016f. A\u017e p\u0159es tv\u00e1\u0159 ti vyhrnu sukni a uk\u00e1\u017ei tvou nahotu pron\u00e1rod\u016fm, kr\u00e1lovstv\u00edm tvou hanbu.\n"
                },
                "6": {
                    "verse_nr": 6,
                    "verse": "Nakyd\u00e1m na tebe ne\u0159\u00e1d, potup\u00edm t\u011b, postav\u00edm na pran\u00fd\u0159.\n"
                },
                "7": {
                    "verse_nr": 7,
                    "verse": "Kdokoli t\u011b spat\u0159\u00ed, prchne od tebe. \u0158ekne: \"Ninive propadlo z\u00e1hub\u011b, kdo se nad n\u00edm ustrne?\" Kde vyhled\u00e1m ty, kdo by t\u011b pot\u011b\u0161ili?\n"
                },
                "8": {
                    "verse_nr": 8,
                    "verse": "Jsi snad lep\u0161\u00ed, ne\u017e byly Th\u00e9by Am\u00f3novy, tr\u016fn\u00edc\u00ed mezi proudy, obklopeny vodami? Mo\u0159e jim bylo valem, jejich hradby se zdvihaly z mo\u0159e.\n"
                },
                "9": {
                    "verse_nr": 9,
                    "verse": "K\u00fa\u0161 tak mocn\u00fd, Egypt nekone\u010dn\u00fd, P\u00fat i L\u00fabim byly tv\u00fdmi pomocn\u00edky.\n"
                },
                "10": {
                    "verse_nr": 10,
                    "verse": "I Th\u00e9by byly p\u0159es\u00eddleny, ode\u0161ly do zajet\u00ed. Jejich nemluv\u0148ata byla drcena na roz\u00edch v\u0161ech ulic; o jejich slavn\u00e9 se losovalo, v\u0161ichni jejich velmo\u017eov\u00e9 byli spout\u00e1ni \u0159et\u011bzy.\n"
                },
                "11": {
                    "verse_nr": 11,
                    "verse": "I ty se opoj\u00ed\u0161 a bude\u0161 om\u00e1meno. I ty bude\u0161 hledat z\u00e1\u0161titu p\u0159ed nep\u0159\u00edtelem.\n"
                },
                "12": {
                    "verse_nr": 12,
                    "verse": "V\u0161echny tv\u00e9 pevnosti v\u0161ak budou jako f\u00edkovn\u00edky s ran\u00fdmi plody: a\u017e se jimi zat\u0159ese, spadnou do \u00fast tomu, kdo je chce j\u00edst.\n"
                },
                "13": {
                    "verse_nr": 13,
                    "verse": "Tv\u016fj lid uprost\u0159ed tebe jsou baby. Br\u00e1ny tv\u00e9 zem\u011b se doko\u0159\u00e1n otev\u0159ou tv\u00fdm nep\u0159\u00e1tel\u016fm, tv\u00e9 z\u00e1vory poz\u0159e ohe\u0148.\n"
                },
                "14": {
                    "verse_nr": 14,
                    "verse": "Nava\u017e si vodu, ne\u017e bude\u0161 oble\u017eeno! Zpevni sv\u00e1 opevn\u011bn\u00ed! \u0160lapej j\u00edl, hn\u011b\u0165 hl\u00ednu, chop se formy na cihly!\n"
                },
                "15": {
                    "verse_nr": 15,
                    "verse": "Ohe\u0148 t\u011b tam poz\u0159e, vytne me\u010d, poz\u0159e t\u011b jako brouci. By\u0165 v\u00e1s bylo spousta jako brouk\u016f, by\u0165 v\u00e1s bylo spousta jako kobylek,\n"
                },
                "16": {
                    "verse_nr": 16,
                    "verse": "by\u0165 tv\u00fdch p\u0159ekupn\u00edk\u016f bylo v\u00edc ne\u017e nebesk\u00fdch hv\u011bzd, brouci se vykukl\u00ed a odl\u00e9tnou.\n"
                },
                "17": {
                    "verse_nr": 17,
                    "verse": "Tvoji str\u00e1\u017eci jsou jak kobylky, tvoji \u00fa\u0159edn\u00edci jak hejna saran\u010dat: v zimn\u00edm \u010dase zalezou do \u0161kv\u00edr z\u00eddek, ale jak vysvitne slunce, ul\u00e9tnou a nev\u00ed\u0161, kam se pod\u011bly.\n"
                },
                "18": {
                    "verse_nr": 18,
                    "verse": "Ji\u017e d\u0159\u00edmou tvoji past\u00fd\u0159i, asyrsk\u00fd kr\u00e1li, ulehli tvoji vzne\u0161en\u00ed. Tv\u016fj lid je rozehn\u00e1n po hor\u00e1ch, nikdo jej neshrom\u00e1\u017ed\u00ed.\n"
                },
                "19": {
                    "verse_nr": 19,
                    "verse": "Nikdo neo\u0161et\u0159\u00ed tv\u00e9 t\u011b\u017ek\u00e9 poran\u011bn\u00ed, bolestn\u00e1 z\u016fstane tv\u00e1 r\u00e1na. V\u0161ichni, kdo o tob\u011b usly\u0161\u00ed, zatleskaj\u00ed nad tebou v dlan\u011b. V\u017edy\u0165 na koho nedol\u00e9hala bez p\u0159est\u00e1n\u00ed tv\u00e1 zloba?\n"
                }
            }
        }
    }
}